fitting/__init__.py
fitting/convertDataToJson.py
fitting/fittingScript.py
fitting/myapp.py
fitting/scroll.py
fitting_slaven92-0.0.1.dist-info/LICENCE
fitting_slaven92-0.0.1.dist-info/METADATA
fitting_slaven92-0.0.1.dist-info/WHEEL
fitting_slaven92-0.0.1.dist-info/top_level.txt
fitting_slaven92-0.0.1.dist-info/RECORD
