Metadata-Version: 2.1
Name: fitting-slaven92
Version: 0.0.1
Summary: fitting personal data
Home-page: https://github.com/slaven92/fitting
Author: Slaven Tepsic
Author-email: stepsic@icfo.eu
License: UNKNOWN
Platform: UNKNOWN
Classifier: Programming Language :: Python :: 3
Classifier: License :: OSI Approved :: MIT License
Classifier: Operating System :: OS Independent
Requires-Python: >=3.6
